Metadata-Version: 2.1
Name: BulkSmsZim
Version: 1.2.1
Summary: A Helper Library For Sending Text Messages For BulkSmsZimApi
Home-page: https://github.com/MarlvinzW/BulkSmsZim-Api
Author: Marlvin Chihota
Author-email: info@marlvinzw.me
License: UNKNOWN
Download-URL: https://github.com/MarlvinzW/BulkSmsZim-Api
Platform: UNKNOWN
Classifier: Programming Language :: Python :: 3
Classifier: License :: OSI Approved :: MIT License
Classifier: Operating System :: OS Independent
